CHANGES.txt
MANIFEST.in
MIT-LICENSE.txt
README.txt
setup.cfg
setup.py
sharder.ini
sharder/__init__.py
sharder/cache.py
sharder/models.py
sharder/phantom.py
sharder/schema.py
sharder/security.py
sharder/tables.py
sharder/tests.py
sharder/views.py
sharder.egg-info/PKG-INFO
sharder.egg-info/SOURCES.txt
sharder.egg-info/dependency_links.txt
sharder.egg-info/entry_points.txt
sharder.egg-info/not-zip-safe
sharder.egg-info/requires.txt
sharder.egg-info/top_level.txt
sharder/static/base-min.css
sharder/static/empty1.png
sharder/static/jquery-1.6.4.min.js
sharder/static/normalize.css
sharder/static/reset-fonts-grids.css
sharder/static/reset.css
sharder/static/style.css
sharder/support/jquery-1.6.4.min.js
sharder/support/rasterize.js